{
  "5d9dd70be51c2bb12a1e9a6addd0af5dd42aed13": {
    "title": "Theory of games and economic behavior",
    "year": 1945,
    "venue": "100 Years of Math Milestones",
    "citationCount": 10305,
    "processed": true
  },
  "5864e2472ef9e4fe8c1ddbb040b781c48c401690": {
    "title": "A Generalization of von Neumann's Reduction from the Assignment Problem to Zero-Sum Games",
    "year": 2024,
    "venue": "Games and Economic Behavior",
    "citationCount": 0,
    "processed": true
  },
  "d72507c7e49295e042f555628237b7f06c75ffb1": {
    "title": "Stable outcomes in simple cooperative games",
    "year": 2024,
    "venue": "Journal of Mathematical Economics",
    "citationCount": 0,
    "processed": true
  },
  "0ed5e36088cd2aa72e62d0d02f18242ca9eb5f2a": {
    "title": "Best-response equilibrium: an equilibrium in finitely additive mixed strategies",
    "year": 2023,
    "venue": "International Journal of Game Theory",
    "citationCount": 2,
    "processed": true
  },
  "ab14966201951d0fccf945042eae0786b3020a87": {
    "title": "Multi-lateral strategic bargaining without stationarity",
    "year": 2021,
    "venue": "Journal of Mathematical Economics",
    "citationCount": 0,
    "processed": true
  },
  "148c4a48770208fba592544d5e9b0c86178c5b93": {
    "title": "Ever since Allais",
    "year": 2021,
    "venue": "Journal of Political Economy",
    "citationCount": 0,
    "processed": true
  },
  "5e5dafd6c0ff4060a5a39323cb659460e0daa753": {
    "title": "A resolution of St. Petersburg paradox",
    "year": 2021,
    "venue": "Journal of Mathematical Economics",
    "citationCount": 9,
    "processed": true
  },
  "77c11f2d0f0c8818cf02f6da64bcf1af10839934": {
    "title": "Unilaterally competitive games with more than two players",
    "year": 2020,
    "venue": "International Journal of Game Theory",
    "citationCount": 1,
    "processed": true
  },
  "9bcb3ecd4abfb141225488f04b4634258b9ff736": {
    "title": "Cooperative game with nondeterministic returns",
    "year": 2020,
    "venue": "Journal of Mathematical Economics",
    "citationCount": 4,
    "processed": true
  },
  "5e4da1583294ceab0c0d73246ba30d18b66421a0": {
    "title": "Strategic information transmission with sender\u2019s approval",
    "year": 2020,
    "venue": "International Journal of Game Theory",
    "citationCount": 5,
    "processed": true
  },
  "a5315e415c8bec8d41f3299425c3207f053b1ff9": {
    "title": "An additive model of decision making under risk and ambiguity",
    "year": 2019,
    "venue": "Journal of Mathematical Economics",
    "citationCount": 1,
    "processed": true
  },
  "4c7cb4454fb1b404ce6a1b07195ffd788c051652": {
    "title": "Asymmetric majority pillage games",
    "year": 2019,
    "venue": "International Journal of Game Theory",
    "citationCount": 0,
    "processed": true
  },
  "a98f92c9bb51d87db94f779208b8435a67e97bda": {
    "title": "SSB representation of preferences: Weakening of convexity assumptions",
    "year": 2019,
    "venue": "Journal of Mathematical Economics",
    "citationCount": 2,
    "processed": true
  },
  "728f86971b396b1a1aaf1e2d591e968e21e2064d": {
    "title": "Credible Auctions: A Trilemma",
    "year": 2019,
    "venue": "Econometrica",
    "citationCount": 124,
    "processed": true
  },
  "cbaab11cc422cd5ba81057da3a7b2c36f9814f55": {
    "title": "Coalitional Expected Multi\u2010Utility Theory",
    "year": 2019,
    "venue": "Econometrica",
    "citationCount": 34,
    "processed": true
  },
  "dfe28343cffb21795e277aaf377ebc226c44ce5f": {
    "title": "Legitimate equilibrium",
    "year": 2021,
    "venue": "International Journal of Game Theory",
    "citationCount": 1,
    "processed": true
  },
  "8bfda6235607a3b929df89a3bcdd5c1305bc405a": {
    "title": "Delegation in Veto Bargaining",
    "year": 2020,
    "venue": "The American Economic Review",
    "citationCount": 15,
    "processed": true
  },
  "f3def0be628f2f59ee9f3863cf1a21c9bdb26936": {
    "title": "Smart Contracts and the Coase Conjecture",
    "year": 2023,
    "venue": "The American Economic Review",
    "citationCount": 10,
    "processed": true
  },
  "3c7c391bfe54aa96f8b392ae60d6f34285e4beaf": {
    "title": "Credible Persuasion",
    "year": 2022,
    "venue": "Journal of Political Economy",
    "citationCount": 30,
    "processed": true
  },
  "6f94913ed5e03a04fbb6c5834585586797ff9993": {
    "title": "Mechanism Design with Aftermarkets: Cutoff Mechanisms",
    "year": 2020,
    "venue": "Econometrica",
    "citationCount": 67,
    "processed": true
  },
  "5cf4ed7d3a728b919d4a95e9aecc74b221e6e354": {
    "title": "Costless Information and Costly Verification: A Case for Transparency",
    "year": 2019,
    "venue": "Journal of Political Economy",
    "citationCount": 18,
    "processed": true
  },
  "002db94d7e48f503a9453a1f1dd45a2d2d593bcc": {
    "title": "Mechanism Design with Limited Commitment",
    "year": 2018,
    "venue": "Econometrica",
    "citationCount": 43,
    "processed": true
  },
  "f3dbe56983fe8ca07d6e49ce31a9a755b29fed9f": {
    "title": "Revenue Guarantee Equivalence",
    "year": 2018,
    "venue": "The American Economic Review",
    "citationCount": 31,
    "processed": true
  },
  "d3014ec2441dc881769bbd0cd154162ec568bc31": {
    "title": "Bidding in Common\u2010Value Auctions With an Unknown Number of Competitors",
    "year": 2023,
    "venue": "Econometrica",
    "citationCount": 5,
    "processed": true
  },
  "3c5a8d6012297f2b411f858a59472f2f23e35527": {
    "title": "Bilateral trade with a benevolent intermediary",
    "year": 2021,
    "venue": "Theoretical Economics",
    "citationCount": 3,
    "processed": true
  },
  "9ea5edd89eed5d31e5365b63c52ce9c866579cb3": {
    "title": "Expected multi-utility representations of preferences over lotteries",
    "year": 2025,
    "venue": "Journal of Mathematical Economics",
    "citationCount": 0,
    "processed": true
  },
  "db140475061154dcc39ce6f7e1a1b75c7679e09f": {
    "title": "From local utility to neural networks",
    "year": 2024,
    "venue": "Journal of Mathematical Economics",
    "citationCount": 8,
    "processed": true
  },
  "06bf0646f39e2fb68273c78da2cdb624ba166a9e": {
    "title": "A simple model of two-stage choice",
    "year": 2024,
    "venue": "Journal of Mathematical Economics",
    "citationCount": 1,
    "processed": true
  },
  "e3ca26b6e0912113a93467f8fc7e56ea251a815e": {
    "title": "A unified view of the existence of maximals",
    "year": 2021,
    "venue": "Journal of Mathematical Economics",
    "citationCount": 4,
    "processed": true
  },
  "dc0bf951fc68ecc044263c5579339404d5e5a344": {
    "title": "Utilitarianism with and without expected utility",
    "year": 2020,
    "venue": "Journal of Mathematical Economics",
    "citationCount": 34,
    "processed": true
  },
  "aea17b2922bf8dc0f77f2a787b7590b3ec2eb9f1": {
    "title": "Arrovian Aggregation of Convex Preferences",
    "year": 2017,
    "venue": "Econometrica",
    "citationCount": 16,
    "processed": true
  },
  "fdb865bc5a253c53c0bb4d7b8293b644497c62af": {
    "title": "Extreme Points and Majorization: Economic Applications",
    "year": 2020,
    "venue": "Econometrica",
    "citationCount": 110,
    "processed": true
  },
  "0eee045f5c150e0e461bd5f79a11a63606314c20": {
    "title": "Persuasion Meets Delegation",
    "year": 2018,
    "venue": "Econometrica",
    "citationCount": 24,
    "processed": true
  },
  "0c0f091053c91143487c5151754873f9cefabf60": {
    "title": "Regulating a monopolist with uncertain costs without transfers",
    "year": 2022,
    "venue": "Theoretical Economics",
    "citationCount": 17,
    "processed": true
  },
  "2826d7e61fa44659411412376de1536b461c83fe": {
    "title": "Marginal Reputation",
    "year": 2024,
    "venue": "Econometrica",
    "citationCount": 2,
    "processed": true
  },
  "947d0c35629ff028520bd031b9c0f87a92b58845": {
    "title": "Comparisons of standard royalty auctions with seller post-auction effort",
    "year": 2023,
    "venue": "Journal of Mathematical Economics",
    "citationCount": 0,
    "processed": true
  },
  "680cb190402f1712f511b97b9d3d02d8e292dfc0": {
    "title": "Auctions with external incentives: experimental evidence",
    "year": 2020,
    "venue": "International Journal of Game Theory",
    "citationCount": 3,
    "processed": true
  },
  "72d3e7bcc14d06d8ffda1579603b9d9991d6be02": {
    "title": "Consumer Scores and Price Discrimination",
    "year": 2019,
    "venue": "The Review of Economic Studies",
    "citationCount": 91,
    "processed": true
  },
  "382ebd962bfc4f4b5075b1e980bfbc67fcd53c12": {
    "title": "Slow persuasion",
    "year": 2019,
    "venue": "Theoretical Economics",
    "citationCount": 7,
    "processed": true
  },
  "6c7c88290652838d3c1f09238a2de54829d2f928": {
    "title": "Online Privacy and Information Disclosure by Consumers",
    "year": 2020,
    "venue": "The American Economic Review",
    "citationCount": 176,
    "processed": true
  },
  "1dc38ba1413c0be1a68795e6236f8fff24774838": {
    "title": "Relational communication",
    "year": 2019,
    "venue": "Theoretical Economics",
    "citationCount": 22,
    "processed": true
  },
  "93a774e44c6683ce2879c5998959d0ec49276f31": {
    "title": "Information design in multistage games",
    "year": 2018,
    "venue": "Theoretical Economics",
    "citationCount": 20,
    "processed": true
  },
  "fd819002dd9d738639f71dfbee13c3e092feb95a": {
    "title": "Augmenting Markets with Mechanisms",
    "year": 2017,
    "venue": "The Review of Economic Studies",
    "citationCount": 32,
    "processed": true
  },
  "db75c64384f8ab87696ac378dd029e6fca15c3cd": {
    "title": "How to sell in a sequential auction market",
    "year": 2022,
    "venue": "Theoretical Economics",
    "citationCount": 0,
    "processed": true
  },
  "2bd8b106f0f5d6ec8383310f56b60045a76dc0f3": {
    "title": "Take the Goods and Run: Contracting Frictions and Market Power in Supply Chains",
    "year": 2026,
    "venue": "The American Economic Review",
    "citationCount": 3,
    "processed": true
  },
  "a384d16361f03ead44cc4df59aa13bc62484a405": {
    "title": "Bargaining with Mechanisms",
    "year": 2022,
    "venue": "The American Economic Review",
    "citationCount": 4,
    "processed": true
  },
  "ae128edb040baa1e088a0b1dddef7d880e036347": {
    "title": "Social Insurance, Information Revelation, and Lack of Commitment",
    "year": 2014,
    "venue": "Journal of Political Economy",
    "citationCount": 12,
    "processed": true
  },
  "2c3dbf71f4d8392ef1e998b0a79d4a5059bd2d79": {
    "title": "Optimal Auction Design With Common Values: An Informationally-Robust Approach",
    "year": 2020,
    "venue": "Econometrica",
    "citationCount": 86,
    "processed": true
  },
  "88143a32618e630bf845c0a8830c92cbd8146f20": {
    "title": "Countering the Winner\u2019s Curse: Optimal Auction Design in a Common Value Model",
    "year": 2018,
    "venue": "Theoretical Economics",
    "citationCount": 18,
    "processed": true
  },
  "dfa540153a5206cc9f2fbcff4506e5738e9977cf": {
    "title": "Worst\u2010case equilibria in first\u2010price auctions",
    "year": 2024,
    "venue": "Theoretical Economics",
    "citationCount": 2,
    "processed": true
  }
}